mbqc_scheduling-0.1.0.dist-info/METADATA
mbqc_scheduling-0.1.0.dist-info/WHEEL
mbqc_scheduling-0.1.0.dist-info/license_files/LICENSE-APACHE
mbqc_scheduling-0.1.0.dist-info/license_files/LICENSE-MIT
mbqc_scheduling/__init__.py
mbqc_scheduling/probabilistic.py
mbqc_scheduling/_lib.cpython-310-darwin.so
mbqc_scheduling-0.1.0.dist-info/RECORD
