Metadata-Version: 2.1
Name: mbqc_scheduling
Version: 0.1.0
Classifier: License :: OSI Approved :: MIT License
Classifier: License :: OSI Approved :: Apache Software License
License-File: LICENSE-APACHE
License-File: LICENSE-MIT
Summary: Qubit scheduling in Measurement-Based Quantum Computing (MBQC).
Keywords: quantum,mbqc,scheduling,pauli
Author: Jannis Ruh <ruh.j81@gmail.com>
Author-email: Jannis Ruh <ruh.j81@gmail.com>
License: MIT OR Apache-2.0
Requires-Python: >=3.8
Project-URL: Repository, https://github.com/taeruh/mbqc_scheduling
Project-URL: Documentation, https://taeruh.github.io/mbqc_scheduling/
